{"errors":[],"warnings":[],"namedChunkGroups":{"app":{"chunks":[8,7,2],"assets":["webpack-runtime-ce4feb060b1892dfb68f.js","webpack-runtime-ce4feb060b1892dfb68f.js.map","framework-5dd3c501fd049989ea3a.js","framework-5dd3c501fd049989ea3a.js.map","app-84cf8c31dde63436df70.js","app-84cf8c31dde63436df70.js.map"],"children":{},"childAssets":{}},"component---src-pages-404-js":{"chunks":[1,0,3],"assets":["styles.85b2962e780c79c424a2.css","styles-f12963b3798c232a68f6.js","styles-f12963b3798c232a68f6.js.map","commons-e6ecd063e20ef2dc5981.js","commons-e6ecd063e20ef2dc5981.js.map","component---src-pages-404-js-35948b9d1870907b60be.js","component---src-pages-404-js-35948b9d1870907b60be.js.map"],"children":{},"childAssets":{}},"component---src-pages-about-js":{"chunks":[1,0,4],"assets":["styles.85b2962e780c79c424a2.css","styles-f12963b3798c232a68f6.js","styles-f12963b3798c232a68f6.js.map","commons-e6ecd063e20ef2dc5981.js","commons-e6ecd063e20ef2dc5981.js.map","component---src-pages-about-js-83d7f52639b61c5218e9.js","component---src-pages-about-js-83d7f52639b61c5218e9.js.map"],"children":{},"childAssets":{}},"component---src-pages-contact-js":{"chunks":[1,0,5],"assets":["styles.85b2962e780c79c424a2.css","styles-f12963b3798c232a68f6.js","styles-f12963b3798c232a68f6.js.map","commons-e6ecd063e20ef2dc5981.js","commons-e6ecd063e20ef2dc5981.js.map","component---src-pages-contact-js-2edeb29777a53dc0c522.js","component---src-pages-contact-js-2edeb29777a53dc0c522.js.map"],"children":{},"childAssets":{}},"component---src-pages-index-js":{"chunks":[1,0,6],"assets":["styles.85b2962e780c79c424a2.css","styles-f12963b3798c232a68f6.js","styles-f12963b3798c232a68f6.js.map","commons-e6ecd063e20ef2dc5981.js","commons-e6ecd063e20ef2dc5981.js.map","component---src-pages-index-js-0c59e07ee699968d4157.js","component---src-pages-index-js-0c59e07ee699968d4157.js.map"],"children":{},"childAssets":{}}},"assetsByChunkName":{"app":["webpack-runtime-ce4feb060b1892dfb68f.js","framework-5dd3c501fd049989ea3a.js","app-84cf8c31dde63436df70.js"],"component---src-pages-404-js":["styles.85b2962e780c79c424a2.css","styles-f12963b3798c232a68f6.js","commons-e6ecd063e20ef2dc5981.js","component---src-pages-404-js-35948b9d1870907b60be.js"],"component---src-pages-about-js":["styles.85b2962e780c79c424a2.css","styles-f12963b3798c232a68f6.js","commons-e6ecd063e20ef2dc5981.js","component---src-pages-about-js-83d7f52639b61c5218e9.js"],"component---src-pages-contact-js":["styles.85b2962e780c79c424a2.css","styles-f12963b3798c232a68f6.js","commons-e6ecd063e20ef2dc5981.js","component---src-pages-contact-js-2edeb29777a53dc0c522.js"],"component---src-pages-index-js":["styles.85b2962e780c79c424a2.css","styles-f12963b3798c232a68f6.js","commons-e6ecd063e20ef2dc5981.js","component---src-pages-index-js-0c59e07ee699968d4157.js"]}}